geometry/__init__.py
geometry/draw/__init__.py
geometry/draw/draw2d.py
geometry/draw/draw3d.py
geometry/plane/__init__.py
geometry/plane/circle.py
geometry/plane/square.py
geometry/plane/triangle.py
geometry/solid/__init__.py
geometry/solid/cone.py
geometry/solid/cylinder.py
geometry/solid/sphere.py
geometry_py_packaging-3.0.0.dist-info/LICENSE.txt
geometry_py_packaging-3.0.0.dist-info/METADATA
geometry_py_packaging-3.0.0.dist-info/WHEEL
geometry_py_packaging-3.0.0.dist-info/top_level.txt
geometry_py_packaging-3.0.0.dist-info/RECORD
