Metadata-Version: 2.1
Name: geometry-py-packaging
Version: 3.0.0
Summary: Python Packaging Tutorial by Tom Ge
Author-email: TomGe <tom.gt@foxmail.com>
License: Copyright 2024 Tom Ge
Classifier: Programming Language :: Python :: 3.9
Classifier: License :: OSI Approved :: MIT License
Requires-Python: >=3.9
License-File: LICENSE.txt
Requires-Dist: numpy ; python_version >= "3.9"
Requires-Dist: matplotlib ; python_version >= "3.9"
